README.md
gcs_dhelper.py
setup.cfg
setup.py
gcs_dhelper.egg-info/PKG-INFO
gcs_dhelper.egg-info/SOURCES.txt
gcs_dhelper.egg-info/dependency_links.txt
gcs_dhelper.egg-info/requires.txt
gcs_dhelper.egg-info/top_level.txt