Metadata-Version: 1.2
Name: gcs-dhelper
Version: 0.2
Summary: Biblioteca para crer clientes y buckets de forma mas sencilla
Home-page: https://us.tools.publicis.sapient.com/bitbucket/scm/dsda/gcs-dhelper.git
Author: Guillermo Perrone
Author-email: guillermoperronelopez@gmail.com
License: UNKNOWN
Platform: UNKNOWN
Classifier: Development Status :: 3 - Alpha
Classifier: Intended Audience :: Developers
Classifier: Topic :: Software Development :: Build Tools
Classifier: License :: OSI Approved :: MIT License
Classifier: Programming Language :: Python :: 3
Classifier: Programming Language :: Python :: 3.5
Classifier: Programming Language :: Python :: 3.6
Classifier: Programming Language :: Python :: 3.7
Classifier: Programming Language :: Python :: 3.8
Requires-Python: >=3
